Digital_Farming_Solution/Select_options.py
Digital_Farming_Solution/__init__.py
Digital_Farming_Solution-0.1.10.dist-info/METADATA
Digital_Farming_Solution-0.1.10.dist-info/WHEEL
Digital_Farming_Solution-0.1.10.dist-info/top_level.txt
Digital_Farming_Solution-0.1.10.dist-info/RECORD
